MANIFEST.in
README.md
setup.cfg
setup.py
steamspy/__init__.py
steamspy/methods.py
steamspy/objects.py
steamspy.egg-info/PKG-INFO
steamspy.egg-info/SOURCES.txt
steamspy.egg-info/dependency_links.txt
steamspy.egg-info/requires.txt
steamspy.egg-info/top_level.txt