Metadata-Version: 1.1
Name: steamspy
Version: 0.0.2
Summary: Steamspy api wrapper lib.
Home-page: https://github.com/fly/steamspy
Author: Jon Chen
Author-email: bsd@voltaire.sh
License: MIT
Platform: UNKNOWN
Classifier: Intended Audience :: Developers
Classifier: License :: OSI Approved :: Apache Software License
Classifier: Operating System :: POSIX :: Linux
Classifier: Programming Language :: Python
Classifier: Programming Language :: Python :: 3
Classifier: Programming Language :: Python :: 3.2
Classifier: Programming Language :: Python :: 3.3
Classifier: Programming Language :: Python :: 3.4
